{
  "id": "s-000012",
  "type": "showcase",
  "title": "Autumn Lantern Shrine Night 7s",
  "domain": "scene",
  "features": [
    "scene",
    "process",
    "bloom",
    "glow",
    "gradient",
    "text",
    "path",
    "curve-animation"
  ],
  "dsl": [
    "Graph",
    "Background",
    "Scene",
    "Defs",
    "Timeline",
    "Track",
    "Sequence",
    "Layer",
    "Group",
    "Rect",
    "Circle",
    "Line",
    "Path",
    "Text",
    "Ellipse",
    "LinearGradient",
    "RadialGradient",
    "Process",
    "Tex",
    "Pass",
    "Present"
  ],
  "teaches": [
    "Build a Japanese shrine night scene with glowing paper lanterns, torii gate, and falling maple leaves.",
    "Use warm bloom, lantern sweep light pass, and sin-based flicker vignette for amber night atmosphere."
  ],
  "source_path": "showcase/s-000012",
  "demo_url": "",
  "related": [
    "s-000002",
    "s-000008"
  ],
  "requires": [
    "Graph",
    "Scene",
    "Process",
    "Present"
  ]
}
